[
{"title": "further up", "artist": "Static & Ben El & Pitbull"},
{"title": "moral of the story", "artist": "Ashe"},
{"title": "stupid", "artist": "Tate McRae"},
{"title": "about love", "artist": "MARINA"},
{"title": "some say", "artist": "Nea"},
{"title": "breaking me", "artist": "Topic & A7S"},
{"title": "trust", "artist": "Brent Faiyaz"},
{"title": "death bed", "artist": "Powfu Feat. beabadoobee"},
{"title": "whats poppin", "artist": "Jack Harlow"},
{"title": "vibe", "artist": "Cookiee Kawaii"}
]